CHANGELOG.rst
LICENSE
MANIFEST.in
README.rst
setup.py
cmsplugin_text_wrapper/__init__.py
cmsplugin_text_wrapper/__init__.pyc
cmsplugin_text_wrapper/cms_plugins.py
cmsplugin_text_wrapper/cms_plugins.pyc
cmsplugin_text_wrapper/fields.py
cmsplugin_text_wrapper/fields.pyc
cmsplugin_text_wrapper/forms.py
cmsplugin_text_wrapper/forms.pyc
cmsplugin_text_wrapper/models.py
cmsplugin_text_wrapper/models.pyc
cmsplugin_text_wrapper.egg-info/PKG-INFO
cmsplugin_text_wrapper.egg-info/SOURCES.txt
cmsplugin_text_wrapper.egg-info/dependency_links.txt
cmsplugin_text_wrapper.egg-info/not-zip-safe
cmsplugin_text_wrapper.egg-info/requires.txt
cmsplugin_text_wrapper.egg-info/top_level.txt
cmsplugin_text_wrapper/migrations/0001_initial.py
cmsplugin_text_wrapper/migrations/0001_initial.pyc
cmsplugin_text_wrapper/migrations/0002_add_wrapper.py
cmsplugin_text_wrapper/migrations/0002_add_wrapper.pyc
cmsplugin_text_wrapper/migrations/0003_add_field_textwrapper_classes.py
cmsplugin_text_wrapper/migrations/0003_add_field_textwrapper_classes.pyc
cmsplugin_text_wrapper/migrations/__init__.py
cmsplugin_text_wrapper/migrations/__init__.pyc