Metadata-Version: 1.1
Name: cmsplugin-text-wrapper
Version: 0.6
Summary: A django-cms plugin which extends and replaces the shipped text plugin with simple wrapper functionalities.
Home-page: https://github.com/jrief/cmsplugin-text-wrapper
Author: Jacob Rief
Author-email: jacob.rief@gmail.com
License: BSD
Platform: UNKNOWN
Classifier: Development Status :: 4 - Beta
Classifier: Framework :: Django
Classifier: Intended Audience :: Developers
Classifier: License :: OSI Approved :: BSD License
Classifier: Operating System :: OS Independent
Classifier: Programming Language :: Python
Classifier: Topic :: Internet :: WWW/HTTP
